unitc/__init__.py
unitc/units.py
unitc-0.0.6.dist-info/LICENSE
unitc-0.0.6.dist-info/METADATA
unitc-0.0.6.dist-info/WHEEL
unitc-0.0.6.dist-info/top_level.txt
unitc-0.0.6.dist-info/RECORD
