Metadata-Version: 2.1
Name: unitc
Version: 0.0.6
Summary: Measurement units conversion.
Home-page: https://gitlab.com/mnn/unitc
Author: M. Nuño
Author-email: mnunos@outlook.com
Project-URL: Documentation, https://mnn.gitlab.io/unitc/
Project-URL: Source, https://gitlab.com/mnn/unitc
Project-URL: Bug Reports, https://gitlab.com/mnn/unitc/-/issues
Classifier: Development Status :: 4 - Beta
Classifier: Intended Audience :: Science/Research
Classifier: License :: OSI Approved :: MIT License
Classifier: Programming Language :: Python
Requires-Python: >=3.6
License-File: LICENSE
Requires-Dist: numpy
